ivaylo/__init__.py
ivaylo/simple.py
ivaylo-0.0.1.dist-info/LICENSE
ivaylo-0.0.1.dist-info/METADATA
ivaylo-0.0.1.dist-info/WHEEL
ivaylo-0.0.1.dist-info/top_level.txt
ivaylo-0.0.1.dist-info/RECORD
